LICENSE
MANIFEST.in
README.md
README.rst
requirements.txt
setup.cfg
setup.py
tests/__init__.py
tests/base.py
tests/integration/__init__.py
tests/integration/base.py
tests/integration/client_test.py
tests/integration/deployment_test.py
tests/integration/host_test.py
tests/integration/server_test.py
tests/unit/__init__.py
tests/unit/client_test.py
tests/unit/deployment_test.py
tests/unit/host_test.py
tests/unit/server_test.py
wildfly/__init__.py
wildfly/client.py
wildfly/util.py
wildfly/api/__init__.py
wildfly/api/datasource.py
wildfly/api/deployment.py
wildfly/api/host.py
wildfly/api/jms.py
wildfly/api/server.py
wildfly_py.egg-info/PKG-INFO
wildfly_py.egg-info/SOURCES.txt
wildfly_py.egg-info/dependency_links.txt
wildfly_py.egg-info/entry_points.txt
wildfly_py.egg-info/requires.txt
wildfly_py.egg-info/top_level.txt
wildfly_py.egg-info/zip-safe