Metadata-Version: 1.1
Name: wildfly-py
Version: 0.0.7
Summary: WildFly Management Python API
Home-page: https://github.org/cenx-cf/wildfly-py
Author: CENX
Author-email: devops@cenx.com
License: Apache License 2.0
Keywords: cenx wildfly
Platform: UNKNOWN
Classifier: Development Status :: 4 - Beta
Classifier: Environment :: Console
Classifier: Intended Audience :: Developers
Classifier: Operating System :: Unix
Classifier: Programming Language :: Python
Classifier: Topic :: Utilities
